proof_frog/__init__.py
proof_frog/__main__.py
proof_frog/dependencies.py
proof_frog/frog_ast.py
proof_frog/frog_parser.py
proof_frog/proof_engine.py
proof_frog/proof_frog.py
proof_frog/semantic_analysis.py
proof_frog/visitors.py
proof_frog/antlr/Game.g4
proof_frog/antlr/Primitive.g4
proof_frog/antlr/Proof.g4
proof_frog/antlr/Scheme.g4
proof_frog/antlr/Shared.g4
proof_frog/parsing/Game.interp
proof_frog/parsing/Game.tokens
proof_frog/parsing/GameLexer.interp
proof_frog/parsing/GameLexer.py
proof_frog/parsing/GameLexer.tokens
proof_frog/parsing/GameParser.py
proof_frog/parsing/GameVisitor.py
proof_frog/parsing/Primitive.interp
proof_frog/parsing/Primitive.tokens
proof_frog/parsing/PrimitiveLexer.interp
proof_frog/parsing/PrimitiveLexer.py
proof_frog/parsing/PrimitiveLexer.tokens
proof_frog/parsing/PrimitiveParser.py
proof_frog/parsing/PrimitiveVisitor.py
proof_frog/parsing/Proof.interp
proof_frog/parsing/Proof.tokens
proof_frog/parsing/ProofLexer.interp
proof_frog/parsing/ProofLexer.py
proof_frog/parsing/ProofLexer.tokens
proof_frog/parsing/ProofParser.py
proof_frog/parsing/ProofVisitor.py
proof_frog/parsing/Scheme.interp
proof_frog/parsing/Scheme.tokens
proof_frog/parsing/SchemeLexer.interp
proof_frog/parsing/SchemeLexer.py
proof_frog/parsing/SchemeLexer.tokens
proof_frog/parsing/SchemeParser.py
proof_frog/parsing/SchemeVisitor.py
proof_frog/parsing/__init__.py
proof_frog-0.2.0.dist-info/entry_points.txt
proof_frog-0.2.0.dist-info/licenses/LICENSE
proof_frog-0.2.0.dist-info/WHEEL
proof_frog-0.2.0.dist-info/METADATA
proof_frog-0.2.0.dist-info/RECORD
