Metadata-Version: 2.4
Name: proof_frog
Version: 0.2.0
Summary: A tool for verifying game-hopping proofs
Author-email: Ross Evans <rpevans@uwaterloo.ca>
Requires-Python: >=3.11
License-File: LICENSE
Requires-Dist: antlr4-python3-runtime >= 4.13
Requires-Dist: colorama >= 0.4
Requires-Dist: z3-solver >= 4.12
Requires-Dist: sympy >= 1.12
Project-URL: Documentation, https://prooffrog.github.io
Project-URL: Source, https://github.com/ProofFrog/ProofFrog
